ssmptpaf/__init__.py
ssmptpaf/ssmptpaf.py
ssmptpaf-0.1.dist-info/METADATA
ssmptpaf-0.1.dist-info/WHEEL
ssmptpaf-0.1.dist-info/top_level.txt
ssmptpaf-0.1.dist-info/RECORD
